email_auth_remote_admin_override/__init__.py
email_auth_remote_admin_override/apps.py
email_auth_remote_admin_override-1.0.0.dist-info/METADATA
email_auth_remote_admin_override-1.0.0.dist-info/WHEEL
email_auth_remote_admin_override-1.0.0.dist-info/top_level.txt
email_auth_remote_admin_override-1.0.0.dist-info/RECORD
