Metadata-Version: 2.1
Name: email-auth-remote-admin-override
Version: 1.0.0
Summary: Django app that overrides admin base_site.html
Classifier: Programming Language :: Python :: 3
Classifier: Programming Language :: Python :: 3.10
Classifier: Programming Language :: Python :: 3.11
Classifier: Programming Language :: Python :: 3.12
Classifier: Programming Language :: Python :: 3 :: Only
Requires-Python: >=3.11
Requires-Dist: Django >=4.2
